tylisten/__init__.py
tylisten/futstore.py
tylisten/hookspec/__init__.py
tylisten/hookspec/_type.py
tylisten/hookspec/base.py
tylisten/hookspec/static.py
tylisten/hookspec/timeout.py
tylisten/py.typed
tylisten-2.3.1.dist-info/WHEEL
tylisten-2.3.1.dist-info/METADATA
tylisten-2.3.1.dist-info/RECORD
