Metadata-Version: 2.4
Name: tylisten
Version: 2.3.1
Summary: A tiny hook specification library with typing support.
Author: JamzumSum
Author-email: JamzumSum <22952836+JamzumSum@users.noreply.github.com>
License-Expression: MIT
Classifier: Development Status :: 5 - Production/Stable
Classifier: Intended Audience :: Developers
Classifier: Topic :: Software Development :: Libraries :: Python Modules
Classifier: Topic :: Utilities
Classifier: Typing :: Typed
Requires-Dist: typing-extensions>=4.6.0
Requires-Python: >=3.10
Project-URL: Bug Tracker, https://github.com/JamzumSum/tylisten/issues
Project-URL: Documentation, https://jamzumsum.github.io/tylisten
Project-URL: Homepage, https://github.com/JamzumSum/tylisten
Project-URL: Repository, https://github.com/JamzumSum/tylisten
